auto_import_py/__init__.py
auto_import_py/main.py
auto_import_py/py.typed
auto_import_py-0.1.0.dist-info/METADATA
auto_import_py-0.1.0.dist-info/WHEEL
auto_import_py-0.1.0.dist-info/licenses/LICENSE
auto_import_py-0.1.0.dist-info/RECORD
