Metadata-Version: 2.4
Name: auto-import-py
Version: 0.1.0
Summary: Auto import
Author-email: owjs3901 <owjs3901@gmail.com>
License-File: LICENSE
Requires-Python: >=3.9
